[
    {
        "id": "930011",
        "rule_name": "930011",
        "rule_pattern": "1",
        "action": "pass",
        "score": 0,
        "paranoia_level": 1,
        "anomaly_score": 0,
        "severity": "NOTICE",
        "category": "APPLICATION_ATTACK_LFI",
        "phase": 1,
        "tags": "{\"targets\": [\"TX:DETECTION_PARANOIA_LEVEL\"], \"transformations\": [], \"raw_tags\": [\"OWASP_CRS\"], \"operator\": \"less_than\"}",
        "version": "4.16.0-dev",
        "chain_level": 0,
        "parent_rule_id": null,
        "logdata": "Skipped LFI rules for low paranoia",
        "enabled": true
    },
    {
        "id": "930012",
        "rule_name": "930012",
        "rule_pattern": "1",
        "action": "pass",
        "score": 0,
        "paranoia_level": 1,
        "anomaly_score": 0,
        "severity": "NOTICE",
        "category": "APPLICATION_ATTACK_LFI",
        "phase": 2,
        "tags": "{\"targets\": [\"TX:DETECTION_PARANOIA_LEVEL\"], \"transformations\": [], \"raw_tags\": [\"OWASP_CRS\"], \"operator\": \"less_than\"}",
        "version": "4.16.0-dev",
        "chain_level": 0,
        "parent_rule_id": null,
        "logdata": "Skipped LFI rules for low paranoia",
        "enabled": true
    },
    {
        "id": "930100",
        "rule_name": "930100",
        "rule_pattern": "(?i)(?:[/\\x5c]|%(?:2(?:f|5(?:2f|5c|c(?:1%259c|0%25af))|%46)|5c|c(?:0%(?:[2aq]f|5c|9v)|1%(?:[19p]c|8s|af))|(?:bg%q|(?:e|f(?:8%8)?0%8)0%80%a)f|u(?:221[56]|EFC8|F025|002f)|%3(?:2(?:%(?:%6|4)6|F)|5%%63)|1u)|0x(?:2f|5c))(?:\\.(?:%0[01]|\\?)?|\\?\\.?|%(?:2(?:(?:5(?:2|c0%25a))?e|%45)|c0(?:\\.|%[256aef]e)|u(?:(?:ff0|002)e|2024)|%32(?:%(?:%6|4)5|E)|(?:e|f(?:(?:8|c%80)%8)?0%8)0%80%ae)|0x2e){2,3}(?:[/\\x5c]|%(?:2(?:f|5(?:2f|5c|c(?:1%259c|0%25af))|%46)|5c|c(?:0%(?:[2aq]f|5c|9v)|1%(?:[19p]c|8s|af))|(?:bg%q|(?:e|f(?:8%8)?0%8)0%80%a)f|u(?:221[56]|EFC8|F025|002f)|%3(?:2(?:%(?:%6|4)6|F)|5%%63)|1u)|0x(?:2f|5c))",
        "action": "block",
        "score": 10,
        "paranoia_level": 1,
        "anomaly_score": 10,
        "severity": "CRITICAL",
        "category": "APPLICATION_ATTACK_LFI",
        "phase": 2,
        "tags": "{\"targets\": [\"REQUEST_URI_RAW\", \"ARGS\", \"REQUEST_HEADERS\", \"!REQUEST_HEADERS:Referer\", \"FILES\", \"XML:/*\"], \"transformations\": [\"none\"], \"raw_tags\": [\"application-multi\", \"language-multi\", \"platform-multi\", \"attack-lfi\", \"paranoia-level/1\", \"OWASP_CRS\", \"OWASP_CRS/ATTACK-LFI\", \"capec/1000/255/153/126\"], \"operator\": \"regex\"}",
        "version": "4.16.0-dev",
        "chain_level": 0,
        "parent_rule_id": null,
        "logdata": "Path Traversal Attack",
        "enabled": true
    },
    {
        "id": "930110",
        "rule_name": "930110",
        "rule_pattern": "(?:(?:^|[\\x5c/;])\\.{2,3}[\\x5c/;]|[\\x5c/;]\\.{2,3}[\\x5c/;])",
        "action": "block",
        "score": 10,
        "paranoia_level": 1,
        "anomaly_score": 10,
        "severity": "CRITICAL",
        "category": "APPLICATION_ATTACK_LFI",
        "phase": 2,
        "tags": "{\"targets\": [\"REQUEST_URI_RAW\", \"ARGS\", \"REQUEST_HEADERS\", \"!REQUEST_HEADERS:Referer\", \"FILES\", \"XML:/*\"], \"transformations\": [\"none\", \"utf8toUnicode\", \"urlDecodeUni\", \"removeNulls\", \"cmdLine\"], \"raw_tags\": [\"application-multi\", \"language-multi\", \"platform-multi\", \"attack-lfi\", \"paranoia-level/1\", \"OWASP_CRS\", \"OWASP_CRS/ATTACK-LFI\", \"capec/1000/255/153/126\"], \"operator\": \"regex\"}",
        "version": "4.16.0-dev",
        "chain_level": 0,
        "parent_rule_id": null,
        "logdata": "Path Traversal Attack",
        "enabled": true
    },
    {
        "id": "930120",
        "rule_name": "930120",
        "rule_pattern": "lfi-os-files.data",
        "action": "block",
        "score": 10,
        "paranoia_level": 1,
        "anomaly_score": 10,
        "severity": "CRITICAL",
        "category": "APPLICATION_ATTACK_LFI",
        "phase": 2,
        "tags": "{\"targets\": [\"REQUEST_COOKIES\", \"REQUEST_COOKIES_NAMES\", \"ARGS_NAMES\", \"ARGS\", \"XML:/*\"], \"transformations\": [\"none\", \"utf8toUnicode\", \"urlDecodeUni\", \"normalizePathWin\"], \"raw_tags\": [\"application-multi\", \"language-multi\", \"platform-multi\", \"attack-lfi\", \"paranoia-level/1\", \"OWASP_CRS\", \"OWASP_CRS/ATTACK-LFI\", \"capec/1000/255/153/126\", \"PCI/6.5.4\"], \"operator\": \"phrase_match_file\"}",
        "version": "4.16.0-dev",
        "chain_level": 0,
        "parent_rule_id": null,
        "logdata": "OS File Access Attempt",
        "enabled": true
    },
    {
        "id": "930130",
        "rule_name": "930130",
        "rule_pattern": "restricted-files.data",
        "action": "block",
        "score": 10,
        "paranoia_level": 1,
        "anomaly_score": 10,
        "severity": "CRITICAL",
        "category": "APPLICATION_ATTACK_LFI",
        "phase": 1,
        "tags": "{\"targets\": [\"REQUEST_FILENAME\"], \"transformations\": [\"none\", \"utf8toUnicode\", \"urlDecodeUni\", \"normalizePathWin\"], \"raw_tags\": [\"application-multi\", \"language-multi\", \"platform-multi\", \"attack-lfi\", \"paranoia-level/1\", \"OWASP_CRS\", \"OWASP_CRS/ATTACK-LFI\", \"capec/1000/255/153/126\", \"PCI/6.5.4\"], \"operator\": \"phrase_match_file\"}",
        "version": "4.16.0-dev",
        "chain_level": 0,
        "parent_rule_id": null,
        "logdata": "Restricted File Access Attempt",
        "enabled": true
    },
    {
        "id": "930013",
        "rule_name": "930013",
        "rule_pattern": "2",
        "action": "pass",
        "score": 0,
        "paranoia_level": 2,
        "anomaly_score": 0,
        "severity": "NOTICE",
        "category": "APPLICATION_ATTACK_LFI",
        "phase": 1,
        "tags": "{\"targets\": [\"TX:DETECTION_PARANOIA_LEVEL\"], \"transformations\": [], \"raw_tags\": [\"OWASP_CRS\"], \"operator\": \"less_than\"}",
        "version": "4.16.0-dev",
        "chain_level": 0,
        "parent_rule_id": null,
        "logdata": "Skipped LFI rules for low paranoia",
        "enabled": true
    },
    {
        "id": "930014",
        "rule_name": "930014",
        "rule_pattern": "2",
        "action": "pass",
        "score": 0,
        "paranoia_level": 2,
        "anomaly_score": 0,
        "severity": "NOTICE",
        "category": "APPLICATION_ATTACK_LFI",
        "phase": 2,
        "tags": "{\"targets\": [\"TX:DETECTION_PARANOIA_LEVEL\"], \"transformations\": [], \"raw_tags\": [\"OWASP_CRS\"], \"operator\": \"less_than\"}",
        "version": "4.16.0-dev",
        "chain_level": 0,
        "parent_rule_id": null,
        "logdata": "Skipped LFI rules for low paranoia",
        "enabled": true
    },
    {
        "id": "930121",
        "rule_name": "930121",
        "rule_pattern": "lfi-os-files.data",
        "action": "block",
        "score": 10,
        "paranoia_level": 2,
        "anomaly_score": 10,
        "severity": "CRITICAL",
        "category": "APPLICATION_ATTACK_LFI",
        "phase": 1,
        "tags": "{\"targets\": [\"REQUEST_HEADERS:Referer\", \"REQUEST_HEADERS:User-Agent\"], \"transformations\": [\"none\", \"utf8toUnicode\", \"urlDecodeUni\", \"normalizePathWin\"], \"raw_tags\": [\"application-multi\", \"language-multi\", \"platform-multi\", \"attack-lfi\", \"paranoia-level/2\", \"OWASP_CRS\", \"OWASP_CRS/ATTACK-LFI\", \"capec/1000/255/153/126\", \"PCI/6.5.4\"], \"operator\": \"phrase_match_file\"}",
        "version": "4.16.0-dev",
        "chain_level": 0,
        "parent_rule_id": null,
        "logdata": "OS File Access in Headers",
        "enabled": true
    },
    {
        "id": "930015",
        "rule_name": "930015",
        "rule_pattern": "3",
        "action": "pass",
        "score": 0,
        "paranoia_level": 3,
        "anomaly_score": 0,
        "severity": "NOTICE",
        "category": "APPLICATION_ATTACK_LFI",
        "phase": 1,
        "tags": "{\"targets\": [\"TX:DETECTION_PARANOIA_LEVEL\"], \"transformations\": [], \"raw_tags\": [\"OWASP_CRS\"], \"operator\": \"less_than\"}",
        "version": "4.16.0-dev",
        "chain_level": 0,
        "parent_rule_id": null,
        "logdata": "Skipped LFI rules for low paranoia",
        "enabled": true
    },
    {
        "id": "930016",
        "rule_name": "930016",
        "rule_pattern": "3",
        "action": "pass",
        "score": 0,
        "paranoia_level": 3,
        "anomaly_score": 0,
        "severity": "NOTICE",
        "category": "APPLICATION_ATTACK_LFI",
        "phase": 2,
        "tags": "{\"targets\": [\"TX:DETECTION_PARANOIA_LEVEL\"], \"transformations\": [], \"raw_tags\": [\"OWASP_CRS\"], \"operator\": \"less_than\"}",
        "version": "4.16.0-dev",
        "chain_level": 0,
        "parent_rule_id": null,
        "logdata": "Skipped LFI rules for low paranoia",
        "enabled": true
    },
    {
        "id": "930017",
        "rule_name": "930017",
        "rule_pattern": "4",
        "action": "pass",
        "score": 0,
        "paranoia_level": 4,
        "anomaly_score": 0,
        "severity": "NOTICE",
        "category": "APPLICATION_ATTACK_LFI",
        "phase": 1,
        "tags": "{\"targets\": [\"TX:DETECTION_PARANOIA_LEVEL\"], \"transformations\": [], \"raw_tags\": [\"OWASP_CRS\"], \"operator\": \"less_than\"}",
        "version": "4.16.0-dev",
        "chain_level": 0,
        "parent_rule_id": null,
        "logdata": "Skipped LFI rules for low paranoia",
        "enabled": true
    },
    {
        "id": "930018",
        "rule_name": "930018",
        "rule_pattern": "4",
        "action": "pass",
        "score": 0,
        "paranoia_level": 4,
        "anomaly_score": 0,
        "severity": "NOTICE",
        "category": "APPLICATION_ATTACK_LFI",
        "phase": 2,
        "tags": "{\"targets\": [\"TX:DETECTION_PARANOIA_LEVEL\"], \"transformations\": [], \"raw_tags\": [\"OWASP_CRS\"], \"operator\": \"less_than\"}",
        "version": "4.16.0-dev",
        "chain_level": 0,
        "parent_rule_id": null,
        "logdata": "Skipped LFI rules for low paranoia",
        "enabled": true
    }
]